tmuxprocess.py
tmuxprocess-0.2.0.dist-info/METADATA
tmuxprocess-0.2.0.dist-info/RECORD
tmuxprocess-0.2.0.dist-info/WHEEL
tmuxprocess-0.2.0.dist-info/top_level.txt
