Metadata-Version: 2.1
Name: tmuxprocess
Version: 0.2.0
Summary: Redirect I/O from processes to different tmux windows
Home-page: https://github.com/mrahtz/tmuxprocess
Author: Matthew Rahtz
Author-email: matthew.rahtz@gmail.com
License: UNKNOWN
Keywords: multiprocessing process tmux
Platform: UNKNOWN
Classifier: Development Status :: 5 - Production/Stable
Classifier: Intended Audience :: Developers
Classifier: Topic :: Utilities
Classifier: License :: OSI Approved :: MIT License
Classifier: Programming Language :: Python :: 2
Classifier: Programming Language :: Python :: 3
